pytest_moto/__init__.py
pytest_moto/plugin.py
pytest_moto-0.1.1.dist-info/DESCRIPTION.rst
pytest_moto-0.1.1.dist-info/entry_points.txt
pytest_moto-0.1.1.dist-info/metadata.json
pytest_moto-0.1.1.dist-info/METADATA
pytest_moto-0.1.1.dist-info/top_level.txt
pytest_moto-0.1.1.dist-info/WHEEL
pytest_moto-0.1.1.dist-info/RECORD
