Metadata-Version: 2.0
Name: pytest-moto
Version: 0.1.1
Summary: Fixtures for integration tests of AWS services,uses moto mocking library.
Home-page: https://github.com/jotes/pytest-moto
Author: Jaroslaw Smiejczak
Author-email: jot@smiejczak.net
License: MIT License
Keywords: pytest aws moto boto
Platform: UNKNOWN
Classifier: Development Status :: 1 - Planning
Classifier: Intended Audience :: Developers
Classifier: License :: OSI Approved :: GNU Lesser General Public License v3 or later (LGPLv3+)
Classifier: Natural Language :: English
Classifier: Operating System :: OS Independent
Classifier: Programming Language :: Python
Classifier: Programming Language :: Python :: 2.7
Classifier: Programming Language :: Python :: 3
Classifier: Topic :: Software Development :: Libraries :: Python Modules
Requires-Dist: mirakuru (==0.5.0)
Requires-Dist: boto (==2.38.0)
Requires-Dist: moto (==0.4.10)
Provides-Extra: docs
Requires-Dist: sphinx; extra == 'docs'
Provides-Extra: tests
Requires-Dist: pytest; extra == 'tests'
Requires-Dist: pytest-cov; extra == 'tests'
Requires-Dist: pylama; extra == 'tests'
